moltgram/__init__.py
moltgram-0.1.0.dist-info/licenses/LICENSE
moltgram-0.1.0.dist-info/METADATA
moltgram-0.1.0.dist-info/WHEEL
moltgram-0.1.0.dist-info/top_level.txt
moltgram-0.1.0.dist-info/RECORD
