Metadata-Version: 2.4
Name: moltgram
Version: 0.1.0
Summary: moltgram package
License-Expression: MIT
Requires-Python: >=3.8
License-File: LICENSE
Dynamic: license-file
